pyforcis/__init__.py
pyforcis/cache.py
pyforcis/cli.py
pyforcis/config.py
pyforcis/dataset.py
pyforcis/devices.py
pyforcis/parquetio.py
pyforcis/py.typed
pyforcis/terminal.py
pyforcis/versioning.py
pyforcis-0.0.2.dist-info/METADATA
pyforcis-0.0.2.dist-info/WHEEL
pyforcis-0.0.2.dist-info/entry_points.txt
pyforcis-0.0.2.dist-info/licenses/LICENSE
pyforcis-0.0.2.dist-info/RECORD
