Metadata-Version: 2.4
Name: pyforcis
Version: 0.0.2
Summary: Lightweight FORCIS versioning/download toolkit with rich CLI (devices, parquet, integrity)
Author: Khalil Hammami
License: GPL-3.0-only
License-File: LICENSE
Classifier: Development Status :: 3 - Alpha
Classifier: Environment :: Console
Classifier: Intended Audience :: Developers
Classifier: Intended Audience :: Science/Research
Classifier: License :: OSI Approved :: GNU General Public License v3 (GPLv3)
Classifier: Operating System :: OS Independent
Classifier: Programming Language :: Python :: 3
Classifier: Programming Language :: Python :: 3 :: Only
Classifier: Programming Language :: Python :: 3.10
Classifier: Programming Language :: Python :: 3.11
Classifier: Programming Language :: Python :: 3.12
Classifier: Topic :: Scientific/Engineering :: Information Analysis
Classifier: Topic :: Utilities
Classifier: Typing :: Typed
Requires-Python: >=3.10
Requires-Dist: rich>=13.7
Provides-Extra: cli
Requires-Dist: rich>=13.7; extra == 'cli'
Provides-Extra: dev
Requires-Dist: mypy; extra == 'dev'
Requires-Dist: pyarrow>=15.0; extra == 'dev'
Requires-Dist: pytest; extra == 'dev'
Requires-Dist: pytest-cov; extra == 'dev'
Requires-Dist: ruff; extra == 'dev'
Provides-Extra: parquet
Requires-Dist: pyarrow>=15.0; extra == 'parquet'
